{
    "$schema": "../../chain.schema.json",
    "chain_name": "mantrachain",
    "status": "live",
    "network_type": "mainnet",
    "pretty_name": "MANTRA",
    "chain_type": "cosmos",
    "chain_id": "mantra-1",
    "bech32_prefix": "mantra",
    "daemon_name": "mantrachaind",
    "node_home": "$HOME/.mantrachain",
    "key_algos": [
        "secp256k1"
    ],
    "slip44": 118,
    "fees": {
        "fee_tokens": [
            {
                "denom": "uom",
                "fixed_min_gas_price": 0.01,
                "low_gas_price": 0.01,
                "average_gas_price": 0.02,
                "high_gas_price": 0.03
            }
        ]
    },
    "staking": {
        "staking_tokens": [
            {
                "denom": "uom"
            }
        ]
    },
    "codebase": {
        "git_repo": "https://github.com/MANTRA-Chain/mantrachain",
        "recommended_version": "1.0.0",
        "compatible_versions": [
            "1.0.0"
        ],
        "cosmos_sdk_version": "0.50.10",
        "consensus": {
            "type": "cometbft",
            "version": "0.38"
        },
        "cosmwasm_version": "0.53",
        "cosmwasm_enabled": true,
        "sdk": {
            "type": "cosmos",
            "version": "0.50.10"
        },
        "cosmwasm": {
            "version": "0.53",
            "enabled": true
        },
        "versions": [
            {
                "name": "1.0.0-rc3",
                "recommended_version": "1.0.0-rc3",
                "compatible_versions": [
                    "1.0.0-rc3"
                ],
                "cosmos_sdk_version": "0.50.10",
                "consensus": {
                    "type": "cometbft",
                    "version": "0.38"
                },
                "cosmwasm_version": "0.53",
                "cosmwasm_enabled": true,
                "sdk": {
                    "type": "cosmos",
                    "version": "0.50.10"
                },
                "cosmwasm": {
                    "version": "0.53",
                    "enabled": true
                }
            }
        ]
    },
    "peers": {
        "seeds": [
            {
                "id": "32276da966637722914411e16ca91bd37dcd1c28",
                "address": "35.220.157.87:26656"
            },
            {
                "id": "9f5235b418c87af4302619705d0bf4748249ca6b",
                "address": "34.18.33.96:26656"
            },
            {
                "id": "b0acfd505bb4bc0c39d095663d310c253de18210",
                "address": "34.130.121.222:26656"
            }
        ]
    },
    "apis": {
        "rpc": [
            {
                "address": "https://rpc.mantrachain.io",
                "provider": "MANTRACHAIN"
            }
        ],
        "rest": [
            {
                "address": "https://api.mantrachain.io",
                "provider": "MANTRACHAIN"
            }
        ],
        "grpc": [
            {
                "address": "https://grpc.mantrachain.io",
                "provider": "MANTRACHAIN"
            }
        ]
    },
    "logo_URIs": {
        "png": "https://raw.githubusercontent.com/cosmos/chain-registry/master/mantrachain/images/OM-Prim-Col.png",
        "svg": "https://raw.githubusercontent.com/cosmos/chain-registry/master/mantrachain/images/OM-Prim-Col.svg"
    },
    "explorers": [
    ],
    "keywords": [
        "rwa",
        "wasm",
        "staking"
    ],
    "images": [
        {
            "image_sync": {
                "chain_name": "mantrachain",
                "base_denom": "uom"
            },
            "png": "https://raw.githubusercontent.com/cosmos/chain-registry/master/mantrachain/images/OM-Prim-Col.png",
            "svg": "https://raw.githubusercontent.com/cosmos/chain-registry/master/mantrachain/images/OM-Prim-Col.svg",
            "theme": {
                "circle": false,
                "primary_color_hex": "#fba0c1"
            }
        }
    ]
}
