{
  "$schema": "../versions.schema.json",
  "chain_name": "divine",
  "versions": [
    {
      "name": "v1.0.0",
      "recommended_version": "v1.0.0",
      "compatible_versions": [
        "v1.0.0"
      ],
      "consensus": {
        "type": "cometbft",
        "version": "v0.38.17"
      },
      "cosmwasm": {
        "enabled": false
      },
      "language": {
        "type": "go",
        "version": "1.24.5"
      },
      "sdk": {
        "type": "cosmos",
        "version": "v0.53.3"
      },
      "ibc": {
        "type": "go",
        "version": "v10.2.0"
      }
    }
  ]
}