{
  "$schema": "../../versions.schema.json",
  "chain_name": "provenancetestnet",
  "versions": [
    {
      "name": "bouvardia-rc2",
      "tag": "v1.26.0",
      "height": 33257888,
      "recommended_version": "v1.26.0",
      "compatible_versions": [
        "v1.26.0"
      ],
      "consensus": {
        "type": "cometbft",
        "version": "0.38.19"
      },
      "binaries": {
        "linux/amd64": "https://github.com/provenance-io/provenance/releases/download/v1.26.0/provenance-linux-amd64-v1.26.0.zip"
      },
      "sdk": {
        "type": "cosmos",
        "version": "0.50.14"
      },
      "cosmwasm": {
        "version": "0.52",
        "enabled": true
      },
      "ibc": {
        "type": "go",
        "version": "8.6.1",
        "ics_enabled": [
          "ics20-1",
          "ics27-1"
        ]
      }
    },
    {
      "name": "carnation-rc1",
      "tag": "v1.27.2",
      "height": 33853666,
      "recommended_version": "v1.27.2",
      "compatible_versions": [
        "v1.27.2"
      ],
      "consensus": {
        "type": "cometbft",
        "version": "0.38.21"
      },
      "binaries": {
        "linux/amd64": "https://github.com/provenance-io/provenance/releases/download/v1.27.2/provenance-linux-amd64-v1.27.2.zip"
      },
      "sdk": {
        "type": "cosmos",
        "version": "0.50.14"
      },
      "cosmwasm": {
        "version": "0.52",
        "enabled": true
      },
      "ibc": {
        "type": "go",
        "version": "8.6.1",
        "ics_enabled": [
          "ics20-1",
          "ics27-1"
        ]
      }
    }
  ]
}
