{
  "$schema": "../ibc_data.schema.json",
  "chain_1": {
    "chain_name": "axelar",
    "client_id": "07-tendermint-40",
    "connection_id": "connection-22"
  },
  "chain_2": {
    "chain_name": "secretnetwork",
    "client_id": "07-tendermint-44",
    "connection_id": "connection-26"
  },
  "channels": [
    {
      "chain_1": {
        "channel_id": "channel-12",
        "port_id": "transfer"
      },
      "chain_2": {
        "channel_id": "channel-20",
        "port_id": "transfer"
      },
      "ordering": "unordered",
      "version": "ics20-1",
      "tags": {
        "status": "live",
        "preferred": true,
        "properties": "privacy"
      }
    },
    {
      "chain_1": {
        "channel_id": "channel-69",
        "port_id": "transfer",
        "client_id": "07-tendermint-103",
        "connection_id": "connection-89"
      },
      "chain_2": {
        "channel_id": "channel-61",
        "port_id": "wasm.secret1yxjmepvyl2c25vnt53cr2dpn8amknwausxee83",
        "client_id": "07-tendermint-120",
        "connection_id": "connection-93"
      },
      "ordering": "unordered",
      "version": "ics20-1",
      "tags": {
        "status": "live",
        "preferred": true,
        "properties": "privacy"
      }
    }
  ]
}
