{
  "$schema": "../ibc_data.schema.json",
  "chain_1": {
    "chain_name": "evmos",
    "chain_id": "evmos_9001-2",
    "client_id": "07-tendermint-113",
    "connection_id": "connection-67"
  },
  "chain_2": {
    "chain_name": "kava",
    "chain_id": "kava_2222-10",
    "client_id": "07-tendermint-120",
    "connection_id": "connection-157"
  },
  "channels": [
    {
      "chain_1": {
        "channel_id": "channel-83",
        "port_id": "transfer"
      },
      "chain_2": {
        "channel_id": "channel-117",
        "port_id": "transfer"
      },
      "ordering": "unordered",
      "version": "ics20-1",
      "tags": {
        "preferred": true,
        "status": "ACTIVE"
      }
    }
  ]
}