{
  "$schema": "../ibc_data.schema.json",
  "chain_1": {
    "chain_name": "injective",
    "chain_id": "injective-1",
    "client_id": "07-tendermint-253",
    "connection_id": "connection-245"
  },
  "chain_2": {
    "chain_name": "odin",
    "chain_id": "odin-mainnet-freya",
    "client_id": "07-tendermint-122",
    "connection_id": "connection-85"
  },
  "channels": [
    {
      "chain_1": {
        "channel_id": "channel-214",
        "port_id": "transfer"
      },
      "chain_2": {
        "channel_id": "channel-65",
        "port_id": "transfer"
      },
      "ordering": "unordered",
      "version": "ics20-1",
      "tags": {
        "preferred": true,
        "status": "ACTIVE"
      }
    }
  ]
}