{
  "$schema": "../ibc_data.schema.json",
  "chain_1": {
    "chain_name": "likecoin",
    "chain_id": "likecoin-mainnet-2",
    "client_id": "07-tendermint-16",
    "connection_id": "connection-9"
  },
  "chain_2": {
    "chain_name": "osmosis",
    "chain_id": "osmosis-1",
    "client_id": "07-tendermint-1507",
    "connection_id": "connection-1173"
  },
  "channels": [
    {
      "chain_1": {
        "channel_id": "channel-3",
        "port_id": "transfer"
      },
      "chain_2": {
        "channel_id": "channel-53",
        "port_id": "transfer"
      },
      "ordering": "unordered",
      "version": "ics20-1",
      "tags": {
        "preferred": true,
        "status": "ACTIVE"
      }
    }
  ]
}