{
  "$schema": "../../versions.schema.json",
  "chain_name": "swisstroniktestnet",
  "versions": [
    {
      "name": "v0.1.11-testnet",
      "recommended_version": "v0.1.11-testnet",
      "compatible_versions": [
        "v0.1.11-testnet"
      ],
      "consensus": {
        "type": "cometbft",
        "version": "0.37"
      },
      "next_version_name": "v1.0.1",
      "sdk": {
        "type": "cosmos",
        "version": "0.47"
      },
      "ibc": {
        "type": "go",
        "version": "v7.2.0"
      }
    },
    {
      "name": "v1.0.1",
      "proposal": 1,
      "height": 1969786,
      "recommended_version": "v1.0.1",
      "compatible_versions": [
        "v1.0.1"
      ],
      "consensus": {
        "type": "cometbft",
        "version": "0.37"
      },
      "next_version_name": "v1.0.2",
      "sdk": {
        "type": "cosmos",
        "version": "0.47"
      },
      "ibc": {
        "type": "go",
        "version": "v7.2.0"
      }
    },
    {
      "name": "v1.0.2",
      "height": 5430000,
      "recommended_version": "v1.0.2",
      "compatible_versions": [
        "v1.0.2"
      ],
      "binaries": {
        "linux/amd64": "https://github.com/SigmaGmbH/swisstronik-chain/releases/download/testnet-v1.0.2/swisstronik_1.0.2_amd64.deb.zip"
      },
      "consensus": {
        "type": "cometbft",
        "version": "0.37"
      },
      "next_version_name": "",
      "sdk": {
        "type": "cosmos",
        "version": "0.47"
      },
      "ibc": {
        "type": "go",
        "version": "v7.2.0"
      }
    }
  ]
}