{
  "$schema": "../../chain.schema.json",
  "chain_name": "galacticatestnet",
  "status": "live",
  "network_type": "testnet",
  "pretty_name": "Galactica Protocol Testnet",
  "chain_id": "galactica_9301-1",
  "bech32_prefix": "gala",
  "daemon_name": "galacticad",
  "node_home": "$HOME/.galactica",
  "key_algos": [
    "ethsecp256k1"
  ],
  "slip44": 60,
  "fees": {
    "fee_tokens": [
      {
        "denom": "agnet",
        "fixed_min_gas_price": 10,
        "low_gas_price": 10,
        "average_gas_price": 10,
        "high_gas_price": 20
      }
    ]
  },
  "staking": {
    "staking_tokens": [
      {
        "denom": "agnet"
      }
    ]
  },
  "codebase": {
    "git_repo": "https://github.com/Galactica-corp/galactica",
    "recommended_version": "v0.1.1",
    "compatible_versions": [
      "v0.1.1"
    ],
    "cosmos_sdk_version": "0.46",
    "consensus": {
      "type": "cometbft",
      "version": "0.37"
    },
    "cosmwasm_enabled": false,
    "genesis": {
      "genesis_url": "https://raw.githubusercontent.com/Galactica-corp/networks/main/galactica_9301-1/genesis.json"
    },
    "versions": [
      {
        "name": "v0.1.1",
        "recommended_version": "v0.1.1",
        "compatible_versions": [
          "v0.1.1"
        ],
        "cosmos_sdk_version": "0.46",
        "consensus": {
          "type": "cometbft",
          "version": "0.37"
        },
        "cosmwasm_enabled": false
      }
    ]
  },
  "peers": {
    "seeds": [
      {
        "id": "2b590732225bca0f3f55db543861063c705bcd40",
        "address": "seed01-reticulum.galactica.com:26656",
        "provider": "Galactica"
      },
      {
        "id": "fe758700e25b59b6ba6e2784badcb6024ba1b760",
        "address": "seed02-reticulum.galactica.com:26656",
        "provider": "Galactica"
      },
      {
        "id": "028d8c875660f0e3fb1d893acd0b2220c619625f",
        "address": "seed03-reticulum.galactica.com:26656",
        "provider": "Galactica"
      }
    ],
    "persistent_peers": [
     
    ]
  },
  "apis": {
    "rpc": [
      {
        "address": "https://rpc.galactica.test.pfc.zone/",
        "provider": "PFC"
      }
    ],
    "rest": [
      {
        "address": "https://api.galactica.test.pfc.zone/",
        "provider": "PFC"
      }
    ],
    "grpc": [
      {
        "address": "https://grpc.galactica.test.pfc.zone/",
        "provider": "PFC"
      }
    ]
  },
  "logo_URIs": {
    "png": "https://raw.githubusercontent.com/cosmos/chain-registry/master/galactica/images/galactica.png"
  },
  "explorers": [
    {
      "kind": "ping.pub",
      "url": "https://ping.pfc.zone/galactica-testnet",
      "tx_page": "https://ping.pfc.zone/galactica-testnet/tx/${txHash}",
      "account_page": "https://ping.pfc.zone/galactica-testnet/account/${accountAddress}"
    }
  ],
  "keywords": [
    "testnet"
  ],
  "images": [
    {
      "png": "https://raw.githubusercontent.com/cosmos/chain-registry/master/galactica/images/galactica.png"
    }
  ]
}
